dash_dropdown_tree_select/DashDropdownTreeSelect.py
dash_dropdown_tree_select/__init__.py
dash_dropdown_tree_select/_imports_.py
dash_dropdown_tree_select/dash_dropdown_tree_select.min.js
dash_dropdown_tree_select/dash_dropdown_tree_select.min.js.map
dash_dropdown_tree_select/metadata.json
dash_dropdown_tree_select/package-info.json
dash_dropdown_tree_select-1.0.0.dist-info/LICENSE
dash_dropdown_tree_select-1.0.0.dist-info/METADATA
dash_dropdown_tree_select-1.0.0.dist-info/WHEEL
dash_dropdown_tree_select-1.0.0.dist-info/top_level.txt
dash_dropdown_tree_select-1.0.0.dist-info/RECORD
