Metadata-Version: 2.1
Name: dash-dropdown-tree-select
Version: 1.0.0
Summary: A Dash component for react-dropdown-tree-select
Home-page: UNKNOWN
Author: Wes Jones <westonkjones@gmail.com>
Author-email: UNKNOWN
License: MIT
Platform: UNKNOWN
Classifier: Framework :: Dash
